{
    "cmdrOuterStarNum": 2, 
    "duragPat": "DRANT", 
    "cmdrOuterPat": "HJ\u00d6NUT", 
    "eyeMouthNum": 2, 
    "eyeMouthPat": "NORRIK", 
    "cmdrAcc": 0, 
    "hatAcc": 0, 
    "cansOuterPat": "F\u00c4SK", 
    "cansInnerNum": 282, 
    "faceEarsNum": 428, 
    "duragNum": 4, 
    "caneAcc": 0, 
    "duragAcc": 0, 
    "fangsAcc": 0, 
    "cmdrInnerStarNum": 1, 
    "hairNum": 421, 
    "caneNum": 2, 
    "cansInnerPat": "HURM", 
    "shadesNum": 2, 
    "cmdrOuterStarPat": "BINDA", 
    "coinNum": 18, 
    "cansOuterNum": 216, 
    "hairPat": "GRANIONDO", 
    "coinPat": "ETT\u00c5", 
    "ident": 42, 
    "name": "Titus", 
    "faceEarsPat": "HALLUD", 
    "shadesPat": "NORRIK", 
    "shadesAcc": 0, 
    "cmdrInnerStarPat": "POJE", 
    "canePat": "NORRIK", 
    "cansAcc": 0, 
    "cmdrOuterNum": 0
}